scrapit/__init__.py
scrapit/main.py
scrapit/api/__init__.py
scrapit/api/endpoints.py
scrapit/api/models.py
scrapit/crawler/__init__.py
scrapit/crawler/executor.py
scrapit/crawler/response_builder.py
scrapit/crawler/spider_loader.py
scrapit/utils/__init__.py
scrapit/utils/logging_config.py
scrapit/utils/scrapy_runner.py
scrapit-1.0.3.dist-info/METADATA
scrapit-1.0.3.dist-info/WHEEL
scrapit-1.0.3.dist-info/entry_points.txt
scrapit-1.0.3.dist-info/licenses/LICENCE
scrapit-1.0.3.dist-info/RECORD
