Metadata-Version: 2.4
Name: scrapit
Version: 1.0.3
Summary: FastAPI wrapper for Scrapy that lets you to test Scrapy spiders via the API.
Project-URL: Homepage, https://github.com/farhaduneci/scrapit
Project-URL: Repository, https://github.com/farhaduneci/scrapit
Project-URL: Releases, https://github.com/farhaduneci/scrapit/releases
Project-URL: Issues, https://github.com/farhaduneci/scrapit/issues
Author-email: Farhad Uneci <farhaduneci@gmail.com>
License: MIT License
License-File: LICENCE
Keywords: api,crawler,fastapi,scrapy,scrapyrt,spider
Classifier: Development Status :: 4 - Beta
Classifier: Framework :: FastAPI
Classifier: License :: OSI Approved :: MIT License
Classifier: Programming Language :: Python :: 3
Classifier: Programming Language :: Python :: 3.9
Classifier: Programming Language :: Python :: 3.10
Classifier: Topic :: Internet :: WWW/HTTP :: Indexing/Search
Classifier: Topic :: Software Development :: Libraries :: Python Modules
Requires-Python: >=3.9
Requires-Dist: fastapi>=0.104.0
Requires-Dist: pydantic>=2.0.0
Requires-Dist: scrapy>=2.8.0
Requires-Dist: twine>=6.2.0
Requires-Dist: typer>=0.9.0
Requires-Dist: uvicorn[standard]>=0.24.0
Provides-Extra: dev
Requires-Dist: deptry>=0.23.0; extra == 'dev'
Requires-Dist: ruff>=0.11.4; extra == 'dev'
Requires-Dist: twine>=6.1.0; extra == 'dev'
